{
  "columns": [
    {
      "name": "Id",
      "type": "string",
      "references": null
    },
    {
      "name": "QuestKey",
      "type": "foreignrow",
      "references": "Quest"
    },
    {
      "name": "QuestState",
      "type": "i32",
      "references": null
    },
    {
      "name": "Unknown_0",
      "type": "bool",
      "references": null
    },
    {
      "name": "RewardWindowTake",
      "type": "foreignrow",
      "references": "ClientStrings"
    },
    {
      "name": "RewardWindowTitle",
      "type": "foreignrow",
      "references": "ClientStrings"
    }
  ],
  "data": [
    {
      "Id": "a1q1",
      "QuestKey": 0,
      "QuestState": 3,
      "Unknown_0": false,
      "RewardWindowTake": null,
      "RewardWindowTitle": null
    },
    {
      "Id": "a1q5",
      "QuestKey": 1,
      "QuestState": 42,
      "Unknown_0": false,
      "RewardWindowTake": null,
      "RewardWindowTitle": null
    },
    {
      "Id": "a1q5b",
      "QuestKey": 1,
      "QuestState": 1878,
      "Unknown_0": false,
      "RewardWindowTake": null,
      "RewardWindowTitle": null
    },
    {
      "Id": "a1q4",
      "QuestKey": 2,
      "QuestState": 37,
      "Unknown_0": false,
      "RewardWindowTake": null,
      "RewardWindowTitle": null
    },
    {
      "Id": "a1q4b",
      "QuestKey": 2,
      "QuestState": 2149,
      "Unknown_0": false,
      "RewardWindowTake": null,
      "RewardWindowTitle": null
    },
    {
      "Id": "a1q8",
      "QuestKey": 3,
      "QuestState": 2626,
      "Unknown_0": true,
      "RewardWindowTake": null,
      "RewardWindowTitle": null
    },
    {
      "Id": "a1q7",
      "QuestKey": 4,
      "QuestState": 2626,
      "Unknown_0": true,
      "RewardWindowTake": null,
      "RewardWindowTitle": null
    },
    {
      "Id": "a1q2",
      "QuestKey": 5,
      "QuestState": 7,
      "Unknown_0": false,
      "RewardWindowTake": null,
      "RewardWindowTitle": null
    },
    {
      "Id": "a1q2b",
      "QuestKey": 5,
      "QuestState": 798,
      "Unknown_0": false,
      "RewardWindowTake": null,
      "RewardWindowTitle": null
    },
    {
      "Id": "a1q6",
      "QuestKey": 6,
      "QuestState": 2626,
      "Unknown_0": true,
      "RewardWindowTake": null,
      "RewardWindowTitle": null
    },
    {
      "Id": "a1q3",
      "QuestKey": 7,
      "QuestState": 73,
      "Unknown_0": false,
      "RewardWindowTake": null,
      "RewardWindowTitle": null
    },
    {
      "Id": "a1q9",
      "QuestKey": 8,
      "QuestState": 2626,
      "Unknown_0": true,
      "RewardWindowTake": null,
      "RewardWindowTitle": null
    },
    {
      "Id": "a2q5",
      "QuestKey": 10,
      "QuestState": 2626,
      "Unknown_0": true,
      "RewardWindowTake": null,
      "RewardWindowTitle": null
    },
    {
      "Id": "a2q5b",
      "QuestKey": 10,
      "QuestState": 825,
      "Unknown_0": false,
      "RewardWindowTake": null,
      "RewardWindowTitle": null
    },
    {
      "Id": "a2q6",
      "QuestKey": 11,
      "QuestState": 109,
      "Unknown_0": false,
      "RewardWindowTake": null,
      "RewardWindowTitle": null
    },
    {
      "Id": "a2q10",
      "QuestKey": 12,
      "QuestState": 249,
      "Unknown_0": false,
      "RewardWindowTake": null,
      "RewardWindowTitle": null
    },
    {
      "Id": "a2q4",
      "QuestKey": 13,
      "QuestState": 107,
      "Unknown_0": false,
      "RewardWindowTake": null,
      "RewardWindowTitle": null
    },
    {
      "Id": "a2q9b_tencent",
      "QuestKey": 14,
      "QuestState": 2550,
      "Unknown_0": false,
      "RewardWindowTake": null,
      "RewardWindowTitle": null
    },
    {
      "Id": "a2q7",
      "QuestKey": 15,
      "QuestState": 2626,
      "Unknown_0": true,
      "RewardWindowTake": null,
      "RewardWindowTitle": null
    },
    {
      "Id": "a3q1",
      "QuestKey": 21,
      "QuestState": 174,
      "Unknown_0": false,
      "RewardWindowTake": null,
      "RewardWindowTitle": null
    },
    {
      "Id": "a3q2",
      "QuestKey": 22,
      "QuestState": 2626,
      "Unknown_0": true,
      "RewardWindowTake": null,
      "RewardWindowTitle": null
    },
    {
      "Id": "a3q11",
      "QuestKey": 23,
      "QuestState": 2626,
      "Unknown_0": true,
      "RewardWindowTake": null,
      "RewardWindowTitle": null
    },
    {
      "Id": "a3q4",
      "QuestKey": 25,
      "QuestState": 190,
      "Unknown_0": false,
      "RewardWindowTake": null,
      "RewardWindowTitle": null
    },
    {
      "Id": "a3q5",
      "QuestKey": 26,
      "QuestState": 2626,
      "Unknown_0": true,
      "RewardWindowTake": null,
      "RewardWindowTitle": null
    },
    {
      "Id": "a3q8",
      "QuestKey": 27,
      "QuestState": 213,
      "Unknown_0": false,
      "RewardWindowTake": null,
      "RewardWindowTitle": null
    },
    {
      "Id": "a3q12",
      "QuestKey": 28,
      "QuestState": 494,
      "Unknown_0": false,
      "RewardWindowTake": null,
      "RewardWindowTitle": null
    },
    {
      "Id": "a3q13",
      "QuestKey": 29,
      "QuestState": 198,
      "Unknown_0": false,
      "RewardWindowTake": null,
      "RewardWindowTitle": null
    },
    {
      "Id": "a3q9",
      "QuestKey": 30,
      "QuestState": 2626,
      "Unknown_0": true,
      "RewardWindowTake": null,
      "RewardWindowTitle": null
    },
    {
      "Id": "d2c1",
      "QuestKey": 32,
      "QuestState": 522,
      "Unknown_0": false,
      "RewardWindowTake": null,
      "RewardWindowTitle": null
    },
    {
      "Id": "d2c2",
      "QuestKey": 33,
      "QuestState": 523,
      "Unknown_0": false,
      "RewardWindowTake": null,
      "RewardWindowTitle": null
    },
    {
      "Id": "a4q1",
      "QuestKey": 34,
      "QuestState": 689,
      "Unknown_0": false,
      "RewardWindowTake": null,
      "RewardWindowTitle": null
    },
    {
      "Id": "a4q2",
      "QuestKey": 35,
      "QuestState": 666,
      "Unknown_0": false,
      "RewardWindowTake": null,
      "RewardWindowTitle": null
    },
    {
      "Id": "a4q6",
      "QuestKey": 39,
      "QuestState": 2626,
      "Unknown_0": true,
      "RewardWindowTake": null,
      "RewardWindowTitle": null
    },
    {
      "Id": "a4q6b_tencent",
      "QuestKey": 39,
      "QuestState": 2556,
      "Unknown_0": false,
      "RewardWindowTake": null,
      "RewardWindowTitle": null
    },
    {
      "Id": "bandit_respec",
      "QuestKey": 50,
      "QuestState": 2626,
      "Unknown_0": true,
      "RewardWindowTake": 3863,
      "RewardWindowTitle": 3868
    },
    {
      "Id": "a5q1b",
      "QuestKey": 63,
      "QuestState": 1055,
      "Unknown_0": false,
      "RewardWindowTake": null,
      "RewardWindowTitle": null
    },
    {
      "Id": "a5q2",
      "QuestKey": 64,
      "QuestState": 1063,
      "Unknown_0": false,
      "RewardWindowTake": null,
      "RewardWindowTitle": null
    },
    {
      "Id": "a5q3",
      "QuestKey": 65,
      "QuestState": 2626,
      "Unknown_0": true,
      "RewardWindowTake": null,
      "RewardWindowTitle": null
    },
    {
      "Id": "a5q4",
      "QuestKey": 66,
      "QuestState": 1075,
      "Unknown_0": false,
      "RewardWindowTake": null,
      "RewardWindowTitle": null
    },
    {
      "Id": "a5q5",
      "QuestKey": 67,
      "QuestState": 1081,
      "Unknown_0": false,
      "RewardWindowTake": null,
      "RewardWindowTitle": null
    },
    {
      "Id": "a5q7",
      "QuestKey": 69,
      "QuestState": 2626,
      "Unknown_0": true,
      "RewardWindowTake": null,
      "RewardWindowTitle": null
    },
    {
      "Id": "a6q2",
      "QuestKey": 71,
      "QuestState": 1171,
      "Unknown_0": false,
      "RewardWindowTake": null,
      "RewardWindowTitle": null
    },
    {
      "Id": "a6q3",
      "QuestKey": 72,
      "QuestState": 2626,
      "Unknown_0": true,
      "RewardWindowTake": null,
      "RewardWindowTitle": null
    },
    {
      "Id": "a6q4",
      "QuestKey": 73,
      "QuestState": 2626,
      "Unknown_0": true,
      "RewardWindowTake": null,
      "RewardWindowTitle": null
    },
    {
      "Id": "a6q5",
      "QuestKey": 74,
      "QuestState": 1254,
      "Unknown_0": false,
      "RewardWindowTake": null,
      "RewardWindowTitle": null
    },
    {
      "Id": "a6q6",
      "QuestKey": 75,
      "QuestState": 2626,
      "Unknown_0": true,
      "RewardWindowTake": null,
      "RewardWindowTitle": null
    },
    {
      "Id": "a6q7",
      "QuestKey": 76,
      "QuestState": 2626,
      "Unknown_0": true,
      "RewardWindowTake": null,
      "RewardWindowTitle": null
    },
    {
      "Id": "a7q1",
      "QuestKey": 77,
      "QuestState": 2626,
      "Unknown_0": true,
      "RewardWindowTake": null,
      "RewardWindowTitle": null
    },
    {
      "Id": "a7q2",
      "QuestKey": 78,
      "QuestState": 1279,
      "Unknown_0": false,
      "RewardWindowTake": null,
      "RewardWindowTitle": null
    },
    {
      "Id": "a7q3",
      "QuestKey": 79,
      "QuestState": 2626,
      "Unknown_0": true,
      "RewardWindowTake": null,
      "RewardWindowTitle": null
    },
    {
      "Id": "a7q5",
      "QuestKey": 81,
      "QuestState": 1309,
      "Unknown_0": false,
      "RewardWindowTake": null,
      "RewardWindowTitle": null
    },
    {
      "Id": "a7q6",
      "QuestKey": 82,
      "QuestState": 2626,
      "Unknown_0": true,
      "RewardWindowTake": null,
      "RewardWindowTitle": null
    },
    {
      "Id": "a7q8",
      "QuestKey": 84,
      "QuestState": 1377,
      "Unknown_0": false,
      "RewardWindowTake": null,
      "RewardWindowTitle": null
    },
    {
      "Id": "a7q8_offer",
      "QuestKey": 84,
      "QuestState": 2626,
      "Unknown_0": true,
      "RewardWindowTake": 3863,
      "RewardWindowTitle": 3868
    },
    {
      "Id": "a7q9",
      "QuestKey": 85,
      "QuestState": 2626,
      "Unknown_0": true,
      "RewardWindowTake": null,
      "RewardWindowTitle": null
    },
    {
      "Id": "a8q1",
      "QuestKey": 86,
      "QuestState": 1422,
      "Unknown_0": false,
      "RewardWindowTake": null,
      "RewardWindowTitle": null
    },
    {
      "Id": "a8q4",
      "QuestKey": 89,
      "QuestState": 2626,
      "Unknown_0": true,
      "RewardWindowTake": null,
      "RewardWindowTitle": null
    },
    {
      "Id": "a8q5",
      "QuestKey": 90,
      "QuestState": 1442,
      "Unknown_0": false,
      "RewardWindowTake": null,
      "RewardWindowTitle": null
    },
    {
      "Id": "a8q6",
      "QuestKey": 91,
      "QuestState": 2626,
      "Unknown_0": true,
      "RewardWindowTake": null,
      "RewardWindowTitle": null
    },
    {
      "Id": "a8q7",
      "QuestKey": 92,
      "QuestState": 2626,
      "Unknown_0": true,
      "RewardWindowTake": null,
      "RewardWindowTitle": null
    },
    {
      "Id": "a9q2",
      "QuestKey": 94,
      "QuestState": 2626,
      "Unknown_0": true,
      "RewardWindowTake": null,
      "RewardWindowTitle": null
    },
    {
      "Id": "a9q3",
      "QuestKey": 95,
      "QuestState": 1628,
      "Unknown_0": false,
      "RewardWindowTake": null,
      "RewardWindowTitle": null
    },
    {
      "Id": "a9q4",
      "QuestKey": 96,
      "QuestState": 2626,
      "Unknown_0": true,
      "RewardWindowTake": null,
      "RewardWindowTitle": null
    },
    {
      "Id": "a9q5",
      "QuestKey": 97,
      "QuestState": 2626,
      "Unknown_0": true,
      "RewardWindowTake": null,
      "RewardWindowTitle": null
    },
    {
      "Id": "a9q5_offer",
      "QuestKey": 97,
      "QuestState": 2626,
      "Unknown_0": true,
      "RewardWindowTake": 3863,
      "RewardWindowTitle": 3868
    },
    {
      "Id": "a10q1",
      "QuestKey": 98,
      "QuestState": 1646,
      "Unknown_0": false,
      "RewardWindowTake": null,
      "RewardWindowTitle": null
    },
    {
      "Id": "a10q2",
      "QuestKey": 99,
      "QuestState": 1653,
      "Unknown_0": false,
      "RewardWindowTake": null,
      "RewardWindowTitle": null
    },
    {
      "Id": "a10q3",
      "QuestKey": 100,
      "QuestState": 2626,
      "Unknown_0": true,
      "RewardWindowTake": null,
      "RewardWindowTitle": null
    },
    {
      "Id": "a10q4",
      "QuestKey": 101,
      "QuestState": 2626,
      "Unknown_0": true,
      "RewardWindowTake": null,
      "RewardWindowTitle": null
    },
    {
      "Id": "a10q5",
      "QuestKey": 102,
      "QuestState": 1681,
      "Unknown_0": false,
      "RewardWindowTake": null,
      "RewardWindowTitle": null
    },
    {
      "Id": "a10q6",
      "QuestKey": 103,
      "QuestState": 2626,
      "Unknown_0": true,
      "RewardWindowTake": null,
      "RewardWindowTitle": null
    },
    {
      "Id": "atlas",
      "QuestKey": 175,
      "QuestState": 2626,
      "Unknown_0": false,
      "RewardWindowTake": null,
      "RewardWindowTitle": null
    },
    {
      "Id": "heist_tutorial",
      "QuestKey": 126,
      "QuestState": 2626,
      "Unknown_0": true,
      "RewardWindowTake": 3863,
      "RewardWindowTitle": 3868
    },
    {
      "Id": "heist_quest_karst2",
      "QuestKey": 128,
      "QuestState": 2626,
      "Unknown_0": true,
      "RewardWindowTake": 3863,
      "RewardWindowTitle": 3868
    },
    {
      "Id": "heist_quest_karst3",
      "QuestKey": 129,
      "QuestState": 2626,
      "Unknown_0": true,
      "RewardWindowTake": 3863,
      "RewardWindowTitle": 3868
    },
    {
      "Id": "heist_quest_tibbs2",
      "QuestKey": 131,
      "QuestState": 2626,
      "Unknown_0": true,
      "RewardWindowTake": 3863,
      "RewardWindowTitle": 3868
    },
    {
      "Id": "heist_quest_tullina2",
      "QuestKey": 139,
      "QuestState": 2626,
      "Unknown_0": true,
      "RewardWindowTake": 3863,
      "RewardWindowTitle": 3868
    },
    {
      "Id": "heist_quest_faustus2",
      "QuestKey": 154,
      "QuestState": 2626,
      "Unknown_0": true,
      "RewardWindowTake": 3863,
      "RewardWindowTitle": 3868
    },
    {
      "Id": "heist_quest_kurai4",
      "QuestKey": 159,
      "QuestState": 2626,
      "Unknown_0": false,
      "RewardWindowTake": null,
      "RewardWindowTitle": null
    },
    {
      "Id": "heist_quest_karst1",
      "QuestKey": 127,
      "QuestState": 2626,
      "Unknown_0": false,
      "RewardWindowTake": null,
      "RewardWindowTitle": null
    },
    {
      "Id": "heist_quest_karst2_2",
      "QuestKey": 128,
      "QuestState": 2626,
      "Unknown_0": false,
      "RewardWindowTake": null,
      "RewardWindowTitle": null
    },
    {
      "Id": "heist_quest_karst3_2",
      "QuestKey": 129,
      "QuestState": 2626,
      "Unknown_0": false,
      "RewardWindowTake": null,
      "RewardWindowTitle": null
    },
    {
      "Id": "heist_quest_tibbs1",
      "QuestKey": 130,
      "QuestState": 2626,
      "Unknown_0": false,
      "RewardWindowTake": null,
      "RewardWindowTitle": null
    },
    {
      "Id": "heist_quest_tibbs2_2",
      "QuestKey": 131,
      "QuestState": 2626,
      "Unknown_0": false,
      "RewardWindowTake": null,
      "RewardWindowTitle": null
    },
    {
      "Id": "heist_quest_huck1",
      "QuestKey": 132,
      "QuestState": 2626,
      "Unknown_0": false,
      "RewardWindowTake": null,
      "RewardWindowTitle": null
    },
    {
      "Id": "heist_quest_huck2",
      "QuestKey": 133,
      "QuestState": 2626,
      "Unknown_0": false,
      "RewardWindowTake": null,
      "RewardWindowTitle": null
    },
    {
      "Id": "heist_quest_vinderi1",
      "QuestKey": 134,
      "QuestState": 2626,
      "Unknown_0": false,
      "RewardWindowTake": null,
      "RewardWindowTitle": null
    },
    {
      "Id": "heist_quest_vinderi2",
      "QuestKey": 135,
      "QuestState": 2626,
      "Unknown_0": false,
      "RewardWindowTake": null,
      "RewardWindowTitle": null
    },
    {
      "Id": "heist_quest_gianna1",
      "QuestKey": 136,
      "QuestState": 2626,
      "Unknown_0": false,
      "RewardWindowTake": null,
      "RewardWindowTitle": null
    },
    {
      "Id": "heist_quest_gianna2",
      "QuestKey": 137,
      "QuestState": 2626,
      "Unknown_0": false,
      "RewardWindowTake": null,
      "RewardWindowTitle": null
    },
    {
      "Id": "heist_quest_tullina1",
      "QuestKey": 138,
      "QuestState": 2626,
      "Unknown_0": false,
      "RewardWindowTake": null,
      "RewardWindowTitle": null
    },
    {
      "Id": "heist_quest_tullina2_2",
      "QuestKey": 139,
      "QuestState": 2626,
      "Unknown_0": false,
      "RewardWindowTake": null,
      "RewardWindowTitle": null
    },
    {
      "Id": "heist_quest_niles1",
      "QuestKey": 140,
      "QuestState": 2626,
      "Unknown_0": false,
      "RewardWindowTake": null,
      "RewardWindowTitle": null
    },
    {
      "Id": "heist_quest_niles2",
      "QuestKey": 141,
      "QuestState": 2626,
      "Unknown_0": false,
      "RewardWindowTake": null,
      "RewardWindowTitle": null
    },
    {
      "Id": "heist_quest_nenet1",
      "QuestKey": 142,
      "QuestState": 2626,
      "Unknown_0": false,
      "RewardWindowTake": null,
      "RewardWindowTitle": null
    },
    {
      "Id": "heist_quest_nenet2",
      "QuestKey": 143,
      "QuestState": 2626,
      "Unknown_0": false,
      "RewardWindowTake": null,
      "RewardWindowTitle": null
    },
    {
      "Id": "heist_quest_isla1",
      "QuestKey": 144,
      "QuestState": 2626,
      "Unknown_0": false,
      "RewardWindowTake": null,
      "RewardWindowTitle": null
    },
    {
      "Id": "heist_quest_isla2",
      "QuestKey": 145,
      "QuestState": 2626,
      "Unknown_0": false,
      "RewardWindowTake": null,
      "RewardWindowTitle": null
    },
    {
      "Id": "heist_quest_isla3",
      "QuestKey": 146,
      "QuestState": 2626,
      "Unknown_0": false,
      "RewardWindowTake": null,
      "RewardWindowTitle": null
    },
    {
      "Id": "heist_quest_adiyah1",
      "QuestKey": 147,
      "QuestState": 2626,
      "Unknown_0": false,
      "RewardWindowTake": null,
      "RewardWindowTitle": null
    },
    {
      "Id": "heist_quest_adiyah2",
      "QuestKey": 148,
      "QuestState": 2626,
      "Unknown_0": false,
      "RewardWindowTake": null,
      "RewardWindowTitle": null
    },
    {
      "Id": "heist_quest_adiyah3",
      "QuestKey": 149,
      "QuestState": 2626,
      "Unknown_0": false,
      "RewardWindowTake": null,
      "RewardWindowTitle": null
    },
    {
      "Id": "heist_quest_whakano1",
      "QuestKey": 150,
      "QuestState": 2626,
      "Unknown_0": false,
      "RewardWindowTake": null,
      "RewardWindowTitle": null
    },
    {
      "Id": "heist_quest_whakano2",
      "QuestKey": 151,
      "QuestState": 2626,
      "Unknown_0": false,
      "RewardWindowTake": null,
      "RewardWindowTitle": null
    },
    {
      "Id": "heist_quest_whakano3",
      "QuestKey": 152,
      "QuestState": 2626,
      "Unknown_0": false,
      "RewardWindowTake": null,
      "RewardWindowTitle": null
    },
    {
      "Id": "heist_quest_faustus1",
      "QuestKey": 153,
      "QuestState": 2626,
      "Unknown_0": false,
      "RewardWindowTake": null,
      "RewardWindowTitle": null
    },
    {
      "Id": "heist_quest_faustus2_2",
      "QuestKey": 154,
      "QuestState": 2626,
      "Unknown_0": false,
      "RewardWindowTake": null,
      "RewardWindowTitle": null
    },
    {
      "Id": "heist_quest_faustus3",
      "QuestKey": 155,
      "QuestState": 2626,
      "Unknown_0": false,
      "RewardWindowTake": null,
      "RewardWindowTitle": null
    },
    {
      "Id": "heist_quest_kurai1",
      "QuestKey": 156,
      "QuestState": 2626,
      "Unknown_0": false,
      "RewardWindowTake": null,
      "RewardWindowTitle": null
    },
    {
      "Id": "heist_quest_kurai2",
      "QuestKey": 157,
      "QuestState": 2626,
      "Unknown_0": false,
      "RewardWindowTake": null,
      "RewardWindowTitle": null
    },
    {
      "Id": "heist_quest_kurai3",
      "QuestKey": 158,
      "QuestState": 2626,
      "Unknown_0": false,
      "RewardWindowTake": null,
      "RewardWindowTitle": null
    },
    {
      "Id": "hellscape_tutorial1",
      "QuestKey": 171,
      "QuestState": 2626,
      "Unknown_0": true,
      "RewardWindowTake": 3863,
      "RewardWindowTitle": 3868
    },
    {
      "Id": "voidstones",
      "QuestKey": 107,
      "QuestState": 2626,
      "Unknown_0": true,
      "RewardWindowTake": 3865,
      "RewardWindowTitle": 3868
    },
    {
      "Id": "maven",
      "QuestKey": 161,
      "QuestState": 2626,
      "Unknown_0": true,
      "RewardWindowTake": null,
      "RewardWindowTitle": null
    },
    {
      "Id": "uberelder",
      "QuestKey": 162,
      "QuestState": 2626,
      "Unknown_0": true,
      "RewardWindowTake": null,
      "RewardWindowTitle": null
    },
    {
      "Id": "tangle",
      "QuestKey": 163,
      "QuestState": 2626,
      "Unknown_0": true,
      "RewardWindowTake": null,
      "RewardWindowTitle": null
    },
    {
      "Id": "cleansing_fire",
      "QuestKey": 164,
      "QuestState": 2626,
      "Unknown_0": true,
      "RewardWindowTake": null,
      "RewardWindowTitle": null
    },
    {
      "Id": "tangle_infinite_hunger",
      "QuestKey": 163,
      "QuestState": 2626,
      "Unknown_0": true,
      "RewardWindowTake": null,
      "RewardWindowTitle": null
    },
    {
      "Id": "cleansing_fire_black_star",
      "QuestKey": 164,
      "QuestState": 2626,
      "Unknown_0": true,
      "RewardWindowTake": null,
      "RewardWindowTitle": null
    }
  ]
}